pymof/HVOF.py
pymof/MAOF.py
pymof/MOF.py
pymof/WMOF.py
pymof/__init__.py
pymof-0.7.1.dist-info/licenses/LICENSE
pymof-0.7.1.dist-info/METADATA
pymof-0.7.1.dist-info/WHEEL
pymof-0.7.1.dist-info/top_level.txt
pymof-0.7.1.dist-info/RECORD
