Metadata-Version: 2.4
Name: pymof
Version: 0.7.1
Summary: Mass ratio variance-based outlier factor (MOF)
License-File: LICENSE
Requires-Dist: numpy>=1.23
Requires-Dist: numba>=0.56.0
Requires-Dist: scipy>=1.8.0
Requires-Dist: scikit-learn>=1.2.0
Requires-Dist: matplotlib>=3.5
Dynamic: description
Dynamic: description-content-type
Dynamic: license-file
Dynamic: requires-dist
Dynamic: summary
